{
  "title": "C# Programming Quiz",
  "questions": [
    {
      "id": 1,
      "title": "Which keyword is used to define a class in C#?",
      "answer": "class",
      "options": [ "class", "struct", "interface", "object" ]
    },
    {
      "id": 2,
      "title": "What is the base class for all classes in C#?",
      "answer": "Object",
      "options": [ "Object", "Base", "Main", "System" ]
    },
    {
      "id": 3,
      "title": "Which access modifier provides the most restricted access?",
      "answer": "private",
      "options": [ "public", "private", "protected", "internal" ]
    },
    {
      "id": 4,
      "title": "What does LINQ stand for?",
      "answer": "Language Integrated Query",
      "options": [
        "Language Integrated Query",
        "Linear Query Network",
        "Local Information Query",
        "Language Internet Query"
      ]
    },
    {
      "id": 5,
      "title": "Which method is the entry point of a C# console application?",
      "answer": "Main",
      "options": [ "Start", "Main", "Run", "Initialize" ]
    },
    {
      "id": 6,
      "title": "What is the purpose of the 'using' statement in C#?",
      "answer": "Automatic resource disposal",
      "options": [
        "Import namespaces",
        "Automatic resource disposal",
        "Define variables",
        "Create objects"
      ]
    }
  ]
}